Metadata-Version: 1.1
Name: googledatastore
Version: 6.0.0
Summary: google cloud datastore protobuf client
Home-page: https://github.com/GoogleCloudPlatform/google-cloud-datastore
Author: Google Cloud Datastore Team
Author-email: gcd-discuss@google.com
License: UNKNOWN
Platform: UNKNOWN
Classifier: Development Status :: 5 - Production/Stable
Classifier: Topic :: Database
Classifier: License :: OSI Approved :: Apache Software License
Classifier: Operating System :: OS Independent
Classifier: Programming Language :: Python :: 2
Classifier: Programming Language :: Python :: 2.7
